{"Meta": {"Id": null, "Time": 1696045001.513848, "Extended": {"gitlog": "", "dataver": "1", "debhash": "0", "Annotation": null}}, "Measurements": {"total_bytes_consumed": 1100909954201, "ipquery": {"ipv4": "43.202.157.139"}, "ping_latency": {"google_packet_loss_pct": 0.0, "google_rtt_min_ms": 17.12, "google_rtt_max_ms": 17.194, "google_rtt_avg_ms": 17.157, "google_rtt_mdev_ms": 0.025, "amazon_packet_loss_pct": 0.0, "amazon_rtt_min_ms": 2.037, "amazon_rtt_max_ms": 2.137, "amazon_rtt_avg_ms": 2.105, "amazon_rtt_mdev_ms": 0.024, "wikipedia_packet_loss_pct": 0.0, "wikipedia_rtt_min_ms": 83.345, "wikipedia_rtt_max_ms": 83.427, "wikipedia_rtt_avg_ms": 83.374, "wikipedia_rtt_mdev_ms": 0.024, "youtube_packet_loss_pct": 0.0, "youtube_rtt_min_ms": 17.04, "youtube_rtt_max_ms": 17.159, "youtube_rtt_avg_ms": 17.124, "youtube_rtt_mdev_ms": 0.033, "facebook_packet_loss_pct": 0.0, "facebook_rtt_min_ms": 33.492, "facebook_rtt_max_ms": 33.563, "facebook_rtt_avg_ms": 33.537, "facebook_rtt_mdev_ms": 0.017, "tribune_packet_loss_pct": 0.0, "tribune_rtt_min_ms": 2.683, "tribune_rtt_max_ms": 2.788, "tribune_rtt_avg_ms": 2.712, "tribune_rtt_mdev_ms": 0.032, "suntimes_packet_loss_pct": 0.0, "suntimes_rtt_min_ms": 1.676, "suntimes_rtt_max_ms": 1.764, "suntimes_rtt_avg_ms": 1.722, "suntimes_rtt_mdev_ms": 0.023, "uchicago_packet_loss_pct": 0.0, "uchicago_rtt_min_ms": 187.884, "uchicago_rtt_max_ms": 188.21, "uchicago_rtt_avg_ms": 187.992, "uchicago_rtt_mdev_ms": 0.101, "Chicago_packet_loss_pct": 0.0, "Chicago_rtt_min_ms": 160.004, "Chicago_rtt_max_ms": 160.26, "Chicago_rtt_avg_ms": 160.118, "Chicago_rtt_mdev_ms": 0.076, "Washington_DC_error": "Probe IndexError", "Atlanta_packet_loss_pct": 0.0, "Atlanta_rtt_min_ms": 238.04, "Atlanta_rtt_max_ms": 238.656, "Atlanta_rtt_avg_ms": 238.169, "Atlanta_rtt_mdev_ms": 0.211, "Denver_packet_loss_pct": 0.0, "Denver_rtt_min_ms": 157.538, "Denver_rtt_max_ms": 157.77, "Denver_rtt_avg_ms": 157.606, "Denver_rtt_mdev_ms": 0.081, "Seattle_packet_loss_pct": 0.0, "Seattle_rtt_min_ms": 158.266, "Seattle_rtt_max_ms": 158.567, "Seattle_rtt_avg_ms": 158.384, "Seattle_rtt_mdev_ms": 0.107, "Hong_Kong_packet_loss_pct": 0.0, "Hong_Kong_rtt_min_ms": 93.573, "Hong_Kong_rtt_max_ms": 93.596, "Hong_Kong_rtt_avg_ms": 93.585, "Hong_Kong_rtt_mdev_ms": 0.007, "Sydney_packet_loss_pct": 0.0, "Sydney_rtt_min_ms": 166.213, "Sydney_rtt_max_ms": 166.283, "Sydney_rtt_avg_ms": 166.241, "Sydney_rtt_mdev_ms": 0.024, "Johannesburg_packet_loss_pct": 9.09091, "Johannesburg_rtt_min_ms": 391.857, "Johannesburg_rtt_max_ms": 398.368, "Johannesburg_rtt_avg_ms": 392.671, "Johannesburg_rtt_mdev_ms": 1.914, "Tunis_packet_loss_pct": 0.0, "Tunis_rtt_min_ms": 236.483, "Tunis_rtt_max_ms": 236.775, "Tunis_rtt_avg_ms": 236.672, "Tunis_rtt_mdev_ms": 0.09, "Paris_packet_loss_pct": 9.09091, "Paris_rtt_min_ms": 262.055, "Paris_rtt_max_ms": 263.547, "Paris_rtt_avg_ms": 262.431, "Paris_rtt_mdev_ms": 0.523, "Stockholm_packet_loss_pct": 0.0, "Stockholm_rtt_min_ms": 184.912, "Stockholm_rtt_max_ms": 185.039, "Stockholm_rtt_avg_ms": 184.988, "Stockholm_rtt_mdev_ms": 0.036, "error": true}, "last_mile_rtt": {"1.1.1.1_error": "Probe IndexError", "Cloudflare_DNS_last_mile_ping_packet_loss_pct": 0.0, "Cloudflare_DNS_last_mile_ping_rtt_min_ms": 1.798, "Cloudflare_DNS_last_mile_ping_rtt_max_ms": 2.856, "Cloudflare_DNS_last_mile_ping_rtt_avg_ms": 2.12, "Cloudflare_DNS_last_mile_ping_rtt_mdev_ms": 0.367, "Cloudflare_DNS_last_mile_tr_rtt_min_ms": 1.975, "Cloudflare_DNS_last_mile_tr_rtt_median_ms": 2.06, "Cloudflare_DNS_last_mile_tr_rtt_max_ms": 3.279}, "dns_latency": {"dns_query_avg_ms": 109.0, "dns_query_max_ms": 339, "error": false}, "hops_to_target": {"hops_to_google": 17, "error": false}, "test_bytes_consumed": 0}}