{"Meta": {"Id": null, "Time": 1695934601.673307, "Extended": {"gitlog": "", "dataver": "1", "debhash": "0", "Annotation": null}}, "Measurements": {"total_bytes_consumed": 951847939360, "ipquery": {"ipv4": "43.202.157.139"}, "ping_latency": {"google_packet_loss_pct": 0.0, "google_rtt_min_ms": 22.801, "google_rtt_max_ms": 22.884, "google_rtt_avg_ms": 22.846, "google_rtt_mdev_ms": 0.02, "amazon_packet_loss_pct": 0.0, "amazon_rtt_min_ms": 2.541, "amazon_rtt_max_ms": 2.615, "amazon_rtt_avg_ms": 2.576, "amazon_rtt_mdev_ms": 0.018, "wikipedia_packet_loss_pct": 0.0, "wikipedia_rtt_min_ms": 83.341, "wikipedia_rtt_max_ms": 83.422, "wikipedia_rtt_avg_ms": 83.377, "wikipedia_rtt_mdev_ms": 0.025, "youtube_packet_loss_pct": 0.0, "youtube_rtt_min_ms": 23.036, "youtube_rtt_max_ms": 23.105, "youtube_rtt_avg_ms": 23.074, "youtube_rtt_mdev_ms": 0.016, "facebook_packet_loss_pct": 0.0, "facebook_rtt_min_ms": 33.77, "facebook_rtt_max_ms": 33.923, "facebook_rtt_avg_ms": 33.816, "facebook_rtt_mdev_ms": 0.044, "tribune_packet_loss_pct": 0.0, "tribune_rtt_min_ms": 2.655, "tribune_rtt_max_ms": 2.733, "tribune_rtt_avg_ms": 2.69, "tribune_rtt_mdev_ms": 0.024, "suntimes_packet_loss_pct": 0.0, "suntimes_rtt_min_ms": 1.611, "suntimes_rtt_max_ms": 1.664, "suntimes_rtt_avg_ms": 1.647, "suntimes_rtt_mdev_ms": 0.013, "uchicago_packet_loss_pct": 0.0, "uchicago_rtt_min_ms": 187.835, "uchicago_rtt_max_ms": 188.073, "uchicago_rtt_avg_ms": 187.898, "uchicago_rtt_mdev_ms": 0.065, "Chicago_packet_loss_pct": 0.0, "Chicago_rtt_min_ms": 165.634, "Chicago_rtt_max_ms": 165.966, "Chicago_rtt_avg_ms": 165.82, "Chicago_rtt_mdev_ms": 0.118, "Washington_DC_error": "Probe IndexError", "Atlanta_packet_loss_pct": 0.0, "Atlanta_rtt_min_ms": 238.023, "Atlanta_rtt_max_ms": 238.063, "Atlanta_rtt_avg_ms": 238.045, "Atlanta_rtt_mdev_ms": 0.014, "Denver_packet_loss_pct": 0.0, "Denver_rtt_min_ms": 157.472, "Denver_rtt_max_ms": 157.821, "Denver_rtt_avg_ms": 157.572, "Denver_rtt_mdev_ms": 0.111, "Seattle_packet_loss_pct": 0.0, "Seattle_rtt_min_ms": 158.32, "Seattle_rtt_max_ms": 158.635, "Seattle_rtt_avg_ms": 158.468, "Seattle_rtt_mdev_ms": 0.096, "Hong_Kong_packet_loss_pct": 0.0, "Hong_Kong_rtt_min_ms": 92.508, "Hong_Kong_rtt_max_ms": 92.554, "Hong_Kong_rtt_avg_ms": 92.53, "Hong_Kong_rtt_mdev_ms": 0.011, "Sydney_packet_loss_pct": 0.0, "Sydney_rtt_min_ms": 163.579, "Sydney_rtt_max_ms": 163.658, "Sydney_rtt_avg_ms": 163.609, "Sydney_rtt_mdev_ms": 0.019, "Johannesburg_packet_loss_pct": 9.09091, "Johannesburg_rtt_min_ms": 392.149, "Johannesburg_rtt_max_ms": 409.243, "Johannesburg_rtt_avg_ms": 395.738, "Johannesburg_rtt_mdev_ms": 5.277, "Tunis_packet_loss_pct": 23.0769, "Tunis_rtt_min_ms": 529.338, "Tunis_rtt_max_ms": 544.983, "Tunis_rtt_avg_ms": 536.72, "Tunis_rtt_mdev_ms": 4.724, "Paris_packet_loss_pct": 9.09091, "Paris_rtt_min_ms": 262.493, "Paris_rtt_max_ms": 263.919, "Paris_rtt_avg_ms": 262.718, "Paris_rtt_mdev_ms": 0.409, "Stockholm_packet_loss_pct": 0.0, "Stockholm_rtt_min_ms": 184.92, "Stockholm_rtt_max_ms": 190.063, "Stockholm_rtt_avg_ms": 185.693, "Stockholm_rtt_mdev_ms": 1.507, "error": true}, "last_mile_rtt": {"1.1.1.1_error": "Probe IndexError", "Cloudflare_DNS_last_mile_ping_packet_loss_pct": 0.0, "Cloudflare_DNS_last_mile_ping_rtt_min_ms": 1.815, "Cloudflare_DNS_last_mile_ping_rtt_max_ms": 3.781, "Cloudflare_DNS_last_mile_ping_rtt_avg_ms": 2.505, "Cloudflare_DNS_last_mile_ping_rtt_mdev_ms": 0.593, "Cloudflare_DNS_last_mile_tr_rtt_min_ms": 1.528, "Cloudflare_DNS_last_mile_tr_rtt_median_ms": 1.737, "Cloudflare_DNS_last_mile_tr_rtt_max_ms": 1.829}, "dns_latency": {"dns_query_avg_ms": 95.25, "dns_query_max_ms": 229, "error": false}, "hops_to_target": {"hops_to_google": 17, "error": false}, "test_bytes_consumed": 0}}