{"Meta": {"Id": null, "Time": 1695896767.901359, "Extended": {"gitlog": "", "dataver": "1", "debhash": "0", "Annotation": null}}, "Measurements": {"total_bytes_consumed": 908037158361, "ipquery": {"ipv4": "43.202.157.139"}, "ping_latency": {"google_packet_loss_pct": 0.0, "google_rtt_min_ms": 22.444, "google_rtt_max_ms": 22.532, "google_rtt_avg_ms": 22.48, "google_rtt_mdev_ms": 0.025, "amazon_packet_loss_pct": 0.0, "amazon_rtt_min_ms": 2.733, "amazon_rtt_max_ms": 2.79, "amazon_rtt_avg_ms": 2.769, "amazon_rtt_mdev_ms": 0.013, "wikipedia_packet_loss_pct": 0.0, "wikipedia_rtt_min_ms": 83.359, "wikipedia_rtt_max_ms": 83.397, "wikipedia_rtt_avg_ms": 83.373, "wikipedia_rtt_mdev_ms": 0.012, "youtube_packet_loss_pct": 0.0, "youtube_rtt_min_ms": 17.129, "youtube_rtt_max_ms": 17.208, "youtube_rtt_avg_ms": 17.157, "youtube_rtt_mdev_ms": 0.021, "facebook_packet_loss_pct": 0.0, "facebook_rtt_min_ms": 33.723, "facebook_rtt_max_ms": 33.84, "facebook_rtt_avg_ms": 33.781, "facebook_rtt_mdev_ms": 0.028, "tribune_packet_loss_pct": 0.0, "tribune_rtt_min_ms": 2.681, "tribune_rtt_max_ms": 2.776, "tribune_rtt_avg_ms": 2.709, "tribune_rtt_mdev_ms": 0.025, "suntimes_packet_loss_pct": 0.0, "suntimes_rtt_min_ms": 1.706, "suntimes_rtt_max_ms": 1.751, "suntimes_rtt_avg_ms": 1.722, "suntimes_rtt_mdev_ms": 0.011, "uchicago_packet_loss_pct": 0.0, "uchicago_rtt_min_ms": 187.827, "uchicago_rtt_max_ms": 188.046, "uchicago_rtt_avg_ms": 187.915, "uchicago_rtt_mdev_ms": 0.082, "Chicago_packet_loss_pct": 0.0, "Chicago_rtt_min_ms": 165.707, "Chicago_rtt_max_ms": 174.172, "Chicago_rtt_avg_ms": 166.894, "Chicago_rtt_mdev_ms": 2.458, "Washington_DC_error": "Probe IndexError", "Atlanta_packet_loss_pct": 0.0, "Atlanta_rtt_min_ms": 238.29, "Atlanta_rtt_max_ms": 238.504, "Atlanta_rtt_avg_ms": 238.374, "Atlanta_rtt_mdev_ms": 0.069, "Denver_packet_loss_pct": 0.0, "Denver_rtt_min_ms": 157.555, "Denver_rtt_max_ms": 158.292, "Denver_rtt_avg_ms": 157.808, "Denver_rtt_mdev_ms": 0.244, "Seattle_packet_loss_pct": 0.0, "Seattle_rtt_min_ms": 158.186, "Seattle_rtt_max_ms": 158.394, "Seattle_rtt_avg_ms": 158.295, "Seattle_rtt_mdev_ms": 0.057, "Hong_Kong_packet_loss_pct": 0.0, "Hong_Kong_rtt_min_ms": 90.984, "Hong_Kong_rtt_max_ms": 91.186, "Hong_Kong_rtt_avg_ms": 91.08, "Hong_Kong_rtt_mdev_ms": 0.082, "Sydney_packet_loss_pct": 0.0, "Sydney_rtt_min_ms": 160.941, "Sydney_rtt_max_ms": 161.069, "Sydney_rtt_avg_ms": 160.999, "Sydney_rtt_mdev_ms": 0.036, "Johannesburg_packet_loss_pct": 9.09091, "Johannesburg_rtt_min_ms": 394.981, "Johannesburg_rtt_max_ms": 398.922, "Johannesburg_rtt_avg_ms": 395.9, "Johannesburg_rtt_mdev_ms": 1.284, "Tunis_packet_loss_pct": 0.0, "Tunis_rtt_min_ms": 234.033, "Tunis_rtt_max_ms": 235.409, "Tunis_rtt_avg_ms": 234.356, "Tunis_rtt_mdev_ms": 0.422, "Paris_packet_loss_pct": 9.09091, "Paris_rtt_min_ms": 262.522, "Paris_rtt_max_ms": 322.758, "Paris_rtt_avg_ms": 268.73, "Paris_rtt_mdev_ms": 18.014, "Stockholm_packet_loss_pct": 0.0, "Stockholm_rtt_min_ms": 184.913, "Stockholm_rtt_max_ms": 189.026, "Stockholm_rtt_avg_ms": 185.381, "Stockholm_rtt_mdev_ms": 1.215, "error": true}, "last_mile_rtt": {"Cloudflare_DNS_last_mile_ping_packet_loss_pct": 0.0, "Cloudflare_DNS_last_mile_ping_rtt_min_ms": 0.757, "Cloudflare_DNS_last_mile_ping_rtt_max_ms": 1.194, "Cloudflare_DNS_last_mile_ping_rtt_avg_ms": 0.828, "Cloudflare_DNS_last_mile_ping_rtt_mdev_ms": 0.123, "Cloudflare_DNS_last_mile_tr_rtt_min_ms": 3.276}, "dns_latency": {"dns_query_avg_ms": 172.75, "dns_query_max_ms": 759, "error": false}, "hops_to_target": {"hops_to_google": 18, "error": false}, "test_bytes_consumed": 0}}