{"Meta": {"Id": null, "Time": 1696874503.00351, "Extended": {"gitlog": "", "dataver": "1", "debhash": "0", "Annotation": null}}, "Measurements": {"total_bytes_consumed": 729092788961, "ipquery": {"ipv4": "43.202.157.139"}, "ping_latency": {"google_packet_loss_pct": 0.0, "google_rtt_min_ms": 23.503, "google_rtt_max_ms": 23.563, "google_rtt_avg_ms": 23.533, "google_rtt_mdev_ms": 0.017, "amazon_packet_loss_pct": 0.0, "amazon_rtt_min_ms": 2.489, "amazon_rtt_max_ms": 2.541, "amazon_rtt_avg_ms": 2.518, "amazon_rtt_mdev_ms": 0.017, "wikipedia_packet_loss_pct": 0.0, "wikipedia_rtt_min_ms": 83.37, "wikipedia_rtt_max_ms": 83.475, "wikipedia_rtt_avg_ms": 83.427, "wikipedia_rtt_mdev_ms": 0.028, "youtube_packet_loss_pct": 0.0, "youtube_rtt_min_ms": 33.434, "youtube_rtt_max_ms": 33.717, "youtube_rtt_avg_ms": 33.501, "youtube_rtt_mdev_ms": 0.073, "facebook_packet_loss_pct": 0.0, "facebook_rtt_min_ms": 33.055, "facebook_rtt_max_ms": 33.252, "facebook_rtt_avg_ms": 33.1, "facebook_rtt_mdev_ms": 0.058, "tribune_packet_loss_pct": 0.0, "tribune_rtt_min_ms": 8.287, "tribune_rtt_max_ms": 8.463, "tribune_rtt_avg_ms": 8.341, "tribune_rtt_mdev_ms": 0.049, "suntimes_packet_loss_pct": 0.0, "suntimes_rtt_min_ms": 1.67, "suntimes_rtt_max_ms": 1.887, "suntimes_rtt_avg_ms": 1.737, "suntimes_rtt_mdev_ms": 0.053, "uchicago_packet_loss_pct": 0.0, "uchicago_rtt_min_ms": 188.386, "uchicago_rtt_max_ms": 201.366, "uchicago_rtt_avg_ms": 189.777, "uchicago_rtt_mdev_ms": 3.863, "Chicago_packet_loss_pct": 0.0, "Chicago_rtt_min_ms": 172.018, "Chicago_rtt_max_ms": 173.398, "Chicago_rtt_avg_ms": 172.272, "Chicago_rtt_mdev_ms": 0.413, "Washington_DC_error": "Probe IndexError", "Atlanta_packet_loss_pct": 0.0, "Atlanta_rtt_min_ms": 215.944, "Atlanta_rtt_max_ms": 216.908, "Atlanta_rtt_avg_ms": 216.127, "Atlanta_rtt_mdev_ms": 0.322, "Denver_packet_loss_pct": 0.0, "Denver_rtt_min_ms": 157.612, "Denver_rtt_max_ms": 157.982, "Denver_rtt_avg_ms": 157.698, "Denver_rtt_mdev_ms": 0.111, "Seattle_packet_loss_pct": 0.0, "Seattle_rtt_min_ms": 158.497, "Seattle_rtt_max_ms": 158.793, "Seattle_rtt_avg_ms": 158.646, "Seattle_rtt_mdev_ms": 0.083, "Hong_Kong_packet_loss_pct": 0.0, "Hong_Kong_rtt_min_ms": 95.145, "Hong_Kong_rtt_max_ms": 95.169, "Hong_Kong_rtt_avg_ms": 95.157, "Hong_Kong_rtt_mdev_ms": 0.007, "Sydney_packet_loss_pct": 0.0, "Sydney_rtt_min_ms": 166.218, "Sydney_rtt_max_ms": 166.301, "Sydney_rtt_avg_ms": 166.244, "Sydney_rtt_mdev_ms": 0.024, "Johannesburg_packet_loss_pct": 23.0769, "Johannesburg_rtt_min_ms": 391.141, "Johannesburg_rtt_max_ms": 405.281, "Johannesburg_rtt_avg_ms": 392.946, "Johannesburg_rtt_mdev_ms": 4.148, "Tunis_packet_loss_pct": 9.09091, "Tunis_rtt_min_ms": 316.853, "Tunis_rtt_max_ms": 317.27, "Tunis_rtt_avg_ms": 316.984, "Tunis_rtt_mdev_ms": 0.119, "Paris_packet_loss_pct": 0.0, "Paris_rtt_min_ms": 240.513, "Paris_rtt_max_ms": 243.053, "Paris_rtt_avg_ms": 241.146, "Paris_rtt_mdev_ms": 0.804, "Stockholm_packet_loss_pct": 0.0, "Stockholm_rtt_min_ms": 232.532, "Stockholm_rtt_max_ms": 234.563, "Stockholm_rtt_avg_ms": 232.806, "Stockholm_rtt_mdev_ms": 0.598, "error": true}, "last_mile_rtt": {"1.1.1.1_error": "Probe IndexError", "Cloudflare_DNS_last_mile_ping_packet_loss_pct": 0.0, "Cloudflare_DNS_last_mile_ping_rtt_min_ms": 1.23, "Cloudflare_DNS_last_mile_ping_rtt_max_ms": 13.626, "Cloudflare_DNS_last_mile_ping_rtt_avg_ms": 3.302, "Cloudflare_DNS_last_mile_ping_rtt_mdev_ms": 3.572, "Cloudflare_DNS_last_mile_tr_rtt_min_ms": 1.717, "Cloudflare_DNS_last_mile_tr_rtt_median_ms": 1.758, "Cloudflare_DNS_last_mile_tr_rtt_max_ms": 1.775}, "dns_latency": {"dns_query_avg_ms": 106.5, "dns_query_max_ms": 339, "error": false}, "hops_to_target": {"hops_to_google": 18, "error": false}, "test_bytes_consumed": 0}}