{"Meta": {"Id": null, "Time": 1696384302.699855, "Extended": {"gitlog": "", "dataver": "1", "debhash": "0", "Annotation": null}}, "Measurements": {"total_bytes_consumed": 364117909462, "ipquery": {"ipv4": "43.202.157.139"}, "ping_latency": {"google_packet_loss_pct": 0.0, "google_rtt_min_ms": 17.09, "google_rtt_max_ms": 17.15, "google_rtt_avg_ms": 17.123, "google_rtt_mdev_ms": 0.022, "amazon_packet_loss_pct": 0.0, "amazon_rtt_min_ms": 1.464, "amazon_rtt_max_ms": 1.61, "amazon_rtt_avg_ms": 1.501, "amazon_rtt_mdev_ms": 0.044, "wikipedia_packet_loss_pct": 0.0, "wikipedia_rtt_min_ms": 86.234, "wikipedia_rtt_max_ms": 86.271, "wikipedia_rtt_avg_ms": 86.256, "wikipedia_rtt_mdev_ms": 0.01, "youtube_packet_loss_pct": 0.0, "youtube_rtt_min_ms": 17.082, "youtube_rtt_max_ms": 17.272, "youtube_rtt_avg_ms": 17.171, "youtube_rtt_mdev_ms": 0.047, "facebook_packet_loss_pct": 0.0, "facebook_rtt_min_ms": 33.518, "facebook_rtt_max_ms": 33.693, "facebook_rtt_avg_ms": 33.564, "facebook_rtt_mdev_ms": 0.044, "tribune_packet_loss_pct": 0.0, "tribune_rtt_min_ms": 2.543, "tribune_rtt_max_ms": 2.618, "tribune_rtt_avg_ms": 2.584, "tribune_rtt_mdev_ms": 0.021, "suntimes_packet_loss_pct": 0.0, "suntimes_rtt_min_ms": 1.759, "suntimes_rtt_max_ms": 1.885, "suntimes_rtt_avg_ms": 1.788, "suntimes_rtt_mdev_ms": 0.033, "uchicago_packet_loss_pct": 0.0, "uchicago_rtt_min_ms": 188.146, "uchicago_rtt_max_ms": 188.335, "uchicago_rtt_avg_ms": 188.241, "uchicago_rtt_mdev_ms": 0.063, "Chicago_packet_loss_pct": 0.0, "Chicago_rtt_min_ms": 160.144, "Chicago_rtt_max_ms": 160.613, "Chicago_rtt_avg_ms": 160.292, "Chicago_rtt_mdev_ms": 0.148, "Washington_DC_error": "Probe IndexError", "Atlanta_packet_loss_pct": 0.0, "Atlanta_rtt_min_ms": 214.733, "Atlanta_rtt_max_ms": 215.042, "Atlanta_rtt_avg_ms": 214.819, "Atlanta_rtt_mdev_ms": 0.104, "Denver_packet_loss_pct": 0.0, "Denver_rtt_min_ms": 157.305, "Denver_rtt_max_ms": 157.468, "Denver_rtt_avg_ms": 157.379, "Denver_rtt_mdev_ms": 0.057, "Seattle_packet_loss_pct": 0.0, "Seattle_rtt_min_ms": 158.338, "Seattle_rtt_max_ms": 158.656, "Seattle_rtt_avg_ms": 158.431, "Seattle_rtt_mdev_ms": 0.085, "Hong_Kong_packet_loss_pct": 0.0, "Hong_Kong_rtt_min_ms": 92.655, "Hong_Kong_rtt_max_ms": 92.681, "Hong_Kong_rtt_avg_ms": 92.667, "Hong_Kong_rtt_mdev_ms": 0.006, "Sydney_packet_loss_pct": 0.0, "Sydney_rtt_min_ms": 160.948, "Sydney_rtt_max_ms": 161.104, "Sydney_rtt_avg_ms": 161.045, "Sydney_rtt_mdev_ms": 0.044, "Johannesburg_packet_loss_pct": 9.09091, "Johannesburg_rtt_min_ms": 386.541, "Johannesburg_rtt_max_ms": 386.916, "Johannesburg_rtt_avg_ms": 386.67, "Johannesburg_rtt_mdev_ms": 0.124, "Tunis_packet_loss_pct": 0.0, "Tunis_rtt_min_ms": 248.528, "Tunis_rtt_max_ms": 250.067, "Tunis_rtt_avg_ms": 248.833, "Tunis_rtt_mdev_ms": 0.426, "Paris_packet_loss_pct": 0.0, "Paris_rtt_min_ms": 235.732, "Paris_rtt_max_ms": 239.17, "Paris_rtt_avg_ms": 236.671, "Paris_rtt_mdev_ms": 1.137, "Stockholm_packet_loss_pct": 0.0, "Stockholm_rtt_min_ms": 224.443, "Stockholm_rtt_max_ms": 225.213, "Stockholm_rtt_avg_ms": 224.612, "Stockholm_rtt_mdev_ms": 0.206, "error": true}, "last_mile_rtt": {"1.1.1.1_error": "Probe IndexError", "Cloudflare_DNS_last_mile_ping_packet_loss_pct": 0.0, "Cloudflare_DNS_last_mile_ping_rtt_min_ms": 1.157, "Cloudflare_DNS_last_mile_ping_rtt_max_ms": 9.901, "Cloudflare_DNS_last_mile_ping_rtt_avg_ms": 4.069, "Cloudflare_DNS_last_mile_ping_rtt_mdev_ms": 3.3, "Cloudflare_DNS_last_mile_tr_rtt_min_ms": 1.066, "Cloudflare_DNS_last_mile_tr_rtt_median_ms": 1.08, "Cloudflare_DNS_last_mile_tr_rtt_max_ms": 1.759}, "dns_latency": {"dns_query_avg_ms": 125.25, "dns_query_max_ms": 339, "error": false}, "hops_to_target": {"hops_to_google": 17, "error": false}, "test_bytes_consumed": 0}}