{"Meta": {"Id": null, "Time": 1697046069.685525, "Extended": {"gitlog": "", "dataver": "1", "debhash": "0", "Annotation": null}}, "Measurements": {"total_bytes_consumed": 478969122169, "ipquery": {"ipv4": "18.224.54.214"}, "ping_latency": {"google_packet_loss_pct": 0.0, "google_rtt_min_ms": 17.42, "google_rtt_max_ms": 17.533, "google_rtt_avg_ms": 17.466, "google_rtt_mdev_ms": 0.035, "amazon_packet_loss_pct": 0.0, "amazon_rtt_min_ms": 9.714, "amazon_rtt_max_ms": 9.795, "amazon_rtt_avg_ms": 9.761, "amazon_rtt_mdev_ms": 0.021, "wikipedia_packet_loss_pct": 0.0, "wikipedia_rtt_min_ms": 20.212, "wikipedia_rtt_max_ms": 20.499, "wikipedia_rtt_avg_ms": 20.385, "wikipedia_rtt_mdev_ms": 0.094, "youtube_packet_loss_pct": 0.0, "youtube_rtt_min_ms": 16.702, "youtube_rtt_max_ms": 20.269, "youtube_rtt_avg_ms": 17.078, "youtube_rtt_mdev_ms": 1.063, "facebook_packet_loss_pct": 0.0, "facebook_rtt_min_ms": 9.707, "facebook_rtt_max_ms": 9.819, "facebook_rtt_avg_ms": 9.757, "facebook_rtt_mdev_ms": 0.032, "tribune_packet_loss_pct": 0.0, "tribune_rtt_min_ms": 8.81, "tribune_rtt_max_ms": 8.931, "tribune_rtt_avg_ms": 8.88, "tribune_rtt_mdev_ms": 0.031, "suntimes_packet_loss_pct": 0.0, "suntimes_rtt_min_ms": 1.551, "suntimes_rtt_max_ms": 1.678, "suntimes_rtt_avg_ms": 1.592, "suntimes_rtt_mdev_ms": 0.035, "uchicago_packet_loss_pct": 0.0, "uchicago_rtt_min_ms": 17.261, "uchicago_rtt_max_ms": 36.357, "uchicago_rtt_avg_ms": 19.396, "uchicago_rtt_mdev_ms": 5.663, "Chicago_packet_loss_pct": 0.0, "Chicago_rtt_min_ms": 18.142, "Chicago_rtt_max_ms": 18.371, "Chicago_rtt_avg_ms": 18.248, "Chicago_rtt_mdev_ms": 0.068, "Washington_DC_error": "Probe IndexError", "Atlanta_packet_loss_pct": 0.0, "Atlanta_rtt_min_ms": 23.931, "Atlanta_rtt_max_ms": 24.014, "Atlanta_rtt_avg_ms": 23.969, "Atlanta_rtt_mdev_ms": 0.024, "Denver_packet_loss_pct": 0.0, "Denver_rtt_min_ms": 43.13, "Denver_rtt_max_ms": 43.362, "Denver_rtt_avg_ms": 43.196, "Denver_rtt_mdev_ms": 0.071, "Seattle_packet_loss_pct": 0.0, "Seattle_rtt_min_ms": 62.473, "Seattle_rtt_max_ms": 62.796, "Seattle_rtt_avg_ms": 62.58, "Seattle_rtt_mdev_ms": 0.091, "Hong_Kong_packet_loss_pct": 0.0, "Hong_Kong_rtt_min_ms": 206.653, "Hong_Kong_rtt_max_ms": 208.952, "Hong_Kong_rtt_avg_ms": 206.991, "Hong_Kong_rtt_mdev_ms": 0.672, "Sydney_packet_loss_pct": 0.0, "Sydney_rtt_min_ms": 203.981, "Sydney_rtt_max_ms": 204.096, "Sydney_rtt_avg_ms": 204.046, "Sydney_rtt_mdev_ms": 0.041, "Johannesburg_packet_loss_pct": 0.0, "Johannesburg_rtt_min_ms": 209.218, "Johannesburg_rtt_max_ms": 209.527, "Johannesburg_rtt_avg_ms": 209.36, "Johannesburg_rtt_mdev_ms": 0.09, "Tunis_packet_loss_pct": 0.0, "Tunis_rtt_min_ms": 118.875, "Tunis_rtt_max_ms": 122.007, "Tunis_rtt_avg_ms": 119.263, "Tunis_rtt_mdev_ms": 0.916, "Paris_packet_loss_pct": 0.0, "Paris_rtt_min_ms": 85.428, "Paris_rtt_max_ms": 105.426, "Paris_rtt_avg_ms": 87.808, "Paris_rtt_mdev_ms": 5.902, "Stockholm_packet_loss_pct": 0.0, "Stockholm_rtt_min_ms": 106.134, "Stockholm_rtt_max_ms": 106.5, "Stockholm_rtt_avg_ms": 106.323, "Stockholm_rtt_mdev_ms": 0.116, "error": true}, "last_mile_rtt": {"1.1.1.1_error": "Probe IndexError", "Cloudflare_DNS_last_mile_ping_packet_loss_pct": 0.0, "Cloudflare_DNS_last_mile_ping_rtt_min_ms": 9.112, "Cloudflare_DNS_last_mile_ping_rtt_max_ms": 25.307, "Cloudflare_DNS_last_mile_ping_rtt_avg_ms": 11.108, "Cloudflare_DNS_last_mile_ping_rtt_mdev_ms": 4.74, "Cloudflare_DNS_last_mile_tr_rtt_min_ms": 0.221, "Cloudflare_DNS_last_mile_tr_rtt_median_ms": 0.333, "Cloudflare_DNS_last_mile_tr_rtt_max_ms": 10.009}, "dns_latency": {"dns_query_avg_ms": 16.5, "dns_query_max_ms": 29, "error": false}, "hops_to_target": {"hops_to_google": 18, "error": false}, "test_bytes_consumed": 0}}