{"Meta": {"Id": null, "Time": 1696592472.838042, "Extended": {"gitlog": "", "dataver": "1", "debhash": "0", "Annotation": null}}, "Measurements": {"total_bytes_consumed": 274947734267, "ipquery": {"ipv4": "18.224.54.214"}, "ping_latency": {"google_packet_loss_pct": 0.0, "google_rtt_min_ms": 17.709, "google_rtt_max_ms": 17.767, "google_rtt_avg_ms": 17.747, "google_rtt_mdev_ms": 0.018, "amazon_packet_loss_pct": 0.0, "amazon_rtt_min_ms": 10.513, "amazon_rtt_max_ms": 10.581, "amazon_rtt_avg_ms": 10.566, "amazon_rtt_mdev_ms": 0.019, "wikipedia_packet_loss_pct": 0.0, "wikipedia_rtt_min_ms": 20.074, "wikipedia_rtt_max_ms": 20.377, "wikipedia_rtt_avg_ms": 20.223, "wikipedia_rtt_mdev_ms": 0.089, "youtube_packet_loss_pct": 0.0, "youtube_rtt_min_ms": 17.192, "youtube_rtt_max_ms": 17.259, "youtube_rtt_avg_ms": 17.239, "youtube_rtt_mdev_ms": 0.017, "facebook_packet_loss_pct": 0.0, "facebook_rtt_min_ms": 10.612, "facebook_rtt_max_ms": 10.752, "facebook_rtt_avg_ms": 10.679, "facebook_rtt_mdev_ms": 0.031, "tribune_packet_loss_pct": 0.0, "tribune_rtt_min_ms": 9.015, "tribune_rtt_max_ms": 9.124, "tribune_rtt_avg_ms": 9.053, "tribune_rtt_mdev_ms": 0.027, "suntimes_packet_loss_pct": 0.0, "suntimes_rtt_min_ms": 1.046, "suntimes_rtt_max_ms": 1.095, "suntimes_rtt_avg_ms": 1.085, "suntimes_rtt_mdev_ms": 0.013, "uchicago_packet_loss_pct": 0.0, "uchicago_rtt_min_ms": 18.117, "uchicago_rtt_max_ms": 18.363, "uchicago_rtt_avg_ms": 18.176, "uchicago_rtt_mdev_ms": 0.072, "Chicago_packet_loss_pct": 0.0, "Chicago_rtt_min_ms": 19.242, "Chicago_rtt_max_ms": 20.121, "Chicago_rtt_avg_ms": 19.465, "Chicago_rtt_mdev_ms": 0.279, "Washington_DC_error": "Probe IndexError", "Atlanta_packet_loss_pct": 0.0, "Atlanta_rtt_min_ms": 23.49, "Atlanta_rtt_max_ms": 23.681, "Atlanta_rtt_avg_ms": 23.526, "Atlanta_rtt_mdev_ms": 0.052, "Denver_packet_loss_pct": 0.0, "Denver_rtt_min_ms": 47.381, "Denver_rtt_max_ms": 48.052, "Denver_rtt_avg_ms": 47.478, "Denver_rtt_mdev_ms": 0.191, "Seattle_packet_loss_pct": 0.0, "Seattle_rtt_min_ms": 66.177, "Seattle_rtt_max_ms": 66.465, "Seattle_rtt_avg_ms": 66.32, "Seattle_rtt_mdev_ms": 0.083, "Hong_Kong_packet_loss_pct": 0.0, "Hong_Kong_rtt_min_ms": 205.756, "Hong_Kong_rtt_max_ms": 206.704, "Hong_Kong_rtt_avg_ms": 205.87, "Hong_Kong_rtt_mdev_ms": 0.278, "Sydney_packet_loss_pct": 0.0, "Sydney_rtt_min_ms": 199.498, "Sydney_rtt_max_ms": 199.664, "Sydney_rtt_avg_ms": 199.559, "Sydney_rtt_mdev_ms": 0.045, "Johannesburg_packet_loss_pct": 0.0, "Johannesburg_rtt_min_ms": 210.146, "Johannesburg_rtt_max_ms": 212.322, "Johannesburg_rtt_avg_ms": 210.804, "Johannesburg_rtt_mdev_ms": 0.691, "Tunis_packet_loss_pct": 0.0, "Tunis_rtt_min_ms": 118.953, "Tunis_rtt_max_ms": 119.107, "Tunis_rtt_avg_ms": 119.016, "Tunis_rtt_mdev_ms": 0.041, "Paris_packet_loss_pct": 0.0, "Paris_rtt_min_ms": 85.338, "Paris_rtt_max_ms": 216.752, "Paris_rtt_avg_ms": 99.19, "Paris_rtt_mdev_ms": 39.19, "Stockholm_packet_loss_pct": 0.0, "Stockholm_rtt_min_ms": 105.859, "Stockholm_rtt_max_ms": 106.482, "Stockholm_rtt_avg_ms": 106.072, "Stockholm_rtt_mdev_ms": 0.164, "error": true}, "last_mile_rtt": {"1.1.1.1_error": "Probe IndexError", "Cloudflare_DNS_last_mile_ping_packet_loss_pct": 0.0, "Cloudflare_DNS_last_mile_ping_rtt_min_ms": 8.657, "Cloudflare_DNS_last_mile_ping_rtt_max_ms": 11.28, "Cloudflare_DNS_last_mile_ping_rtt_avg_ms": 9.043, "Cloudflare_DNS_last_mile_ping_rtt_mdev_ms": 0.758, "Cloudflare_DNS_last_mile_tr_rtt_min_ms": 18.621, "Cloudflare_DNS_last_mile_tr_rtt_median_ms": 18.633, "Cloudflare_DNS_last_mile_tr_rtt_max_ms": 8.998}, "dns_latency": {"dns_query_avg_ms": 16.25, "dns_query_max_ms": 30, "error": false}, "hops_to_target": {"hops_to_google": 18, "error": false}, "test_bytes_consumed": 0}}