{"Meta": {"Id": null, "Time": 1695808870.983706, "Extended": {"gitlog": "", "dataver": "1", "debhash": "0", "Annotation": null}}, "Measurements": {"total_bytes_consumed": 1112308623941, "ipquery": {"ipv4": "18.224.54.214"}, "ping_latency": {"google_packet_loss_pct": 0.0, "google_rtt_min_ms": 16.64, "google_rtt_max_ms": 16.716, "google_rtt_avg_ms": 16.693, "google_rtt_mdev_ms": 0.023, "amazon_packet_loss_pct": 0.0, "amazon_rtt_min_ms": 1.062, "amazon_rtt_max_ms": 1.126, "amazon_rtt_avg_ms": 1.105, "amazon_rtt_mdev_ms": 0.017, "wikipedia_packet_loss_pct": 0.0, "wikipedia_rtt_min_ms": 29.505, "wikipedia_rtt_max_ms": 29.724, "wikipedia_rtt_avg_ms": 29.607, "wikipedia_rtt_mdev_ms": 0.07, "youtube_packet_loss_pct": 0.0, "youtube_rtt_min_ms": 17.238, "youtube_rtt_max_ms": 17.309, "youtube_rtt_avg_ms": 17.284, "youtube_rtt_mdev_ms": 0.017, "facebook_packet_loss_pct": 0.0, "facebook_rtt_min_ms": 9.808, "facebook_rtt_max_ms": 9.885, "facebook_rtt_avg_ms": 9.871, "facebook_rtt_mdev_ms": 0.021, "tribune_packet_loss_pct": 0.0, "tribune_rtt_min_ms": 9.755, "tribune_rtt_max_ms": 9.838, "tribune_rtt_avg_ms": 9.774, "tribune_rtt_mdev_ms": 0.022, "suntimes_packet_loss_pct": 0.0, "suntimes_rtt_min_ms": 1.113, "suntimes_rtt_max_ms": 1.128, "suntimes_rtt_avg_ms": 1.119, "suntimes_rtt_mdev_ms": 0.005, "uchicago_packet_loss_pct": 0.0, "uchicago_rtt_min_ms": 17.198, "uchicago_rtt_max_ms": 17.452, "uchicago_rtt_avg_ms": 17.288, "uchicago_rtt_mdev_ms": 0.081, "Chicago_packet_loss_pct": 0.0, "Chicago_rtt_min_ms": 18.28, "Chicago_rtt_max_ms": 24.849, "Chicago_rtt_avg_ms": 19.096, "Chicago_rtt_mdev_ms": 1.92, "Washington_DC_error": "Probe IndexError", "Atlanta_packet_loss_pct": 0.0, "Atlanta_rtt_min_ms": 23.276, "Atlanta_rtt_max_ms": 23.452, "Atlanta_rtt_avg_ms": 23.314, "Atlanta_rtt_mdev_ms": 0.047, "Denver_packet_loss_pct": 0.0, "Denver_rtt_min_ms": 42.436, "Denver_rtt_max_ms": 43.181, "Denver_rtt_avg_ms": 42.552, "Denver_rtt_mdev_ms": 0.213, "Seattle_packet_loss_pct": 0.0, "Seattle_rtt_min_ms": 65.702, "Seattle_rtt_max_ms": 65.917, "Seattle_rtt_avg_ms": 65.82, "Seattle_rtt_mdev_ms": 0.064, "Hong_Kong_packet_loss_pct": 0.0, "Hong_Kong_rtt_min_ms": 202.904, "Hong_Kong_rtt_max_ms": 202.995, "Hong_Kong_rtt_avg_ms": 202.932, "Hong_Kong_rtt_mdev_ms": 0.026, "Sydney_packet_loss_pct": 0.0, "Sydney_rtt_min_ms": 203.079, "Sydney_rtt_max_ms": 203.156, "Sydney_rtt_avg_ms": 203.101, "Sydney_rtt_mdev_ms": 0.021, "Johannesburg_packet_loss_pct": 0.0, "Johannesburg_rtt_min_ms": 209.742, "Johannesburg_rtt_max_ms": 214.714, "Johannesburg_rtt_avg_ms": 210.696, "Johannesburg_rtt_mdev_ms": 1.641, "Tunis_packet_loss_pct": 0.0, "Tunis_rtt_min_ms": 114.123, "Tunis_rtt_max_ms": 114.691, "Tunis_rtt_avg_ms": 114.335, "Tunis_rtt_mdev_ms": 0.16, "Paris_packet_loss_pct": 0.0, "Paris_rtt_min_ms": 85.394, "Paris_rtt_max_ms": 190.182, "Paris_rtt_avg_ms": 95.933, "Paris_rtt_mdev_ms": 31.416, "Stockholm_packet_loss_pct": 0.0, "Stockholm_rtt_min_ms": 107.437, "Stockholm_rtt_max_ms": 109.666, "Stockholm_rtt_avg_ms": 107.822, "Stockholm_rtt_mdev_ms": 0.622, "error": true}, "last_mile_rtt": {"1.1.1.1_error": "Probe IndexError", "Cloudflare_DNS_last_mile_ping_packet_loss_pct": 0.0, "Cloudflare_DNS_last_mile_ping_rtt_min_ms": 9.636, "Cloudflare_DNS_last_mile_ping_rtt_max_ms": 13.181, "Cloudflare_DNS_last_mile_ping_rtt_avg_ms": 10.445, "Cloudflare_DNS_last_mile_ping_rtt_mdev_ms": 1.143, "Cloudflare_DNS_last_mile_tr_rtt_min_ms": 10.167, "Cloudflare_DNS_last_mile_tr_rtt_median_ms": 8.648, "Cloudflare_DNS_last_mile_tr_rtt_max_ms": 9.223}, "dns_latency": {"dns_query_avg_ms": 13.75, "dns_query_max_ms": 30, "error": false}, "hops_to_target": {"hops_to_google": 18, "error": false}, "test_bytes_consumed": 0}}