{"Meta": {"Id": null, "Time": 1695809463.704299, "Extended": {"gitlog": "", "dataver": "1", "debhash": "0", "Annotation": null}}, "Measurements": {"total_bytes_consumed": 1112308623941, "ipquery": {"ipv4": "18.224.54.214"}, "ping_latency": {"google_packet_loss_pct": 0.0, "google_rtt_min_ms": 18.634, "google_rtt_max_ms": 18.694, "google_rtt_avg_ms": 18.669, "google_rtt_mdev_ms": 0.016, "amazon_packet_loss_pct": 0.0, "amazon_rtt_min_ms": 1.07, "amazon_rtt_max_ms": 1.124, "amazon_rtt_avg_ms": 1.108, "amazon_rtt_mdev_ms": 0.013, "wikipedia_packet_loss_pct": 0.0, "wikipedia_rtt_min_ms": 29.507, "wikipedia_rtt_max_ms": 29.782, "wikipedia_rtt_avg_ms": 29.671, "wikipedia_rtt_mdev_ms": 0.078, "youtube_packet_loss_pct": 0.0, "youtube_rtt_min_ms": 17.133, "youtube_rtt_max_ms": 17.187, "youtube_rtt_avg_ms": 17.171, "youtube_rtt_mdev_ms": 0.014, "facebook_packet_loss_pct": 0.0, "facebook_rtt_min_ms": 9.827, "facebook_rtt_max_ms": 9.881, "facebook_rtt_avg_ms": 9.868, "facebook_rtt_mdev_ms": 0.014, "tribune_packet_loss_pct": 0.0, "tribune_rtt_min_ms": 9.739, "tribune_rtt_max_ms": 9.905, "tribune_rtt_avg_ms": 9.776, "tribune_rtt_mdev_ms": 0.045, "suntimes_packet_loss_pct": 0.0, "suntimes_rtt_min_ms": 1.954, "suntimes_rtt_max_ms": 1.997, "suntimes_rtt_avg_ms": 1.979, "suntimes_rtt_mdev_ms": 0.012, "uchicago_packet_loss_pct": 0.0, "uchicago_rtt_min_ms": 17.203, "uchicago_rtt_max_ms": 17.406, "uchicago_rtt_avg_ms": 17.267, "uchicago_rtt_mdev_ms": 0.057, "Chicago_packet_loss_pct": 0.0, "Chicago_rtt_min_ms": 18.225, "Chicago_rtt_max_ms": 20.913, "Chicago_rtt_avg_ms": 19.078, "Chicago_rtt_mdev_ms": 0.999, "Washington_DC_error": "Probe IndexError", "Atlanta_packet_loss_pct": 0.0, "Atlanta_rtt_min_ms": 23.263, "Atlanta_rtt_max_ms": 23.629, "Atlanta_rtt_avg_ms": 23.331, "Atlanta_rtt_mdev_ms": 0.103, "Denver_packet_loss_pct": 0.0, "Denver_rtt_min_ms": 42.424, "Denver_rtt_max_ms": 42.579, "Denver_rtt_avg_ms": 42.457, "Denver_rtt_mdev_ms": 0.043, "Seattle_packet_loss_pct": 0.0, "Seattle_rtt_min_ms": 65.728, "Seattle_rtt_max_ms": 65.934, "Seattle_rtt_avg_ms": 65.826, "Seattle_rtt_mdev_ms": 0.058, "Hong_Kong_packet_loss_pct": 0.0, "Hong_Kong_rtt_min_ms": 203.516, "Hong_Kong_rtt_max_ms": 203.564, "Hong_Kong_rtt_avg_ms": 203.532, "Hong_Kong_rtt_mdev_ms": 0.013, "Sydney_packet_loss_pct": 0.0, "Sydney_rtt_min_ms": 202.997, "Sydney_rtt_max_ms": 203.15, "Sydney_rtt_avg_ms": 203.071, "Sydney_rtt_mdev_ms": 0.051, "Johannesburg_packet_loss_pct": 0.0, "Johannesburg_rtt_min_ms": 209.846, "Johannesburg_rtt_max_ms": 220.631, "Johannesburg_rtt_avg_ms": 211.968, "Johannesburg_rtt_mdev_ms": 3.121, "Tunis_packet_loss_pct": 0.0, "Tunis_rtt_min_ms": 114.101, "Tunis_rtt_max_ms": 114.472, "Tunis_rtt_avg_ms": 114.308, "Tunis_rtt_mdev_ms": 0.093, "Paris_packet_loss_pct": 0.0, "Paris_rtt_min_ms": 85.392, "Paris_rtt_max_ms": 87.107, "Paris_rtt_avg_ms": 85.622, "Paris_rtt_mdev_ms": 0.501, "Stockholm_packet_loss_pct": 0.0, "Stockholm_rtt_min_ms": 105.64, "Stockholm_rtt_max_ms": 106.299, "Stockholm_rtt_avg_ms": 105.861, "Stockholm_rtt_mdev_ms": 0.189, "error": true}, "last_mile_rtt": {"1.1.1.1_error": "Probe IndexError", "Cloudflare_DNS_last_mile_ping_packet_loss_pct": 0.0, "Cloudflare_DNS_last_mile_ping_rtt_min_ms": 9.874, "Cloudflare_DNS_last_mile_ping_rtt_max_ms": 14.795, "Cloudflare_DNS_last_mile_ping_rtt_avg_ms": 10.616, "Cloudflare_DNS_last_mile_ping_rtt_mdev_ms": 1.429, "Cloudflare_DNS_last_mile_tr_rtt_min_ms": 0.201, "Cloudflare_DNS_last_mile_tr_rtt_median_ms": 0.204, "Cloudflare_DNS_last_mile_tr_rtt_max_ms": 9.058}, "dns_latency": {"dns_query_avg_ms": 17.5, "dns_query_max_ms": 30, "error": false}, "hops_to_target": {"hops_to_google": 18, "error": false}, "test_bytes_consumed": 0}}