{"Meta": {"Id": null, "Time": 1696763469.439096, "Extended": {"gitlog": "", "dataver": "1", "debhash": "0", "Annotation": null}}, "Measurements": {"total_bytes_consumed": 885232502503, "ipquery": {"ipv4": "3.71.100.200"}, "ping_latency": {"google_packet_loss_pct": 0.0, "google_rtt_min_ms": 0.611, "google_rtt_max_ms": 0.669, "google_rtt_avg_ms": 0.634, "google_rtt_mdev_ms": 0.016, "amazon_packet_loss_pct": 0.0, "amazon_rtt_min_ms": 0.611, "amazon_rtt_max_ms": 0.68, "amazon_rtt_avg_ms": 0.653, "amazon_rtt_mdev_ms": 0.018, "wikipedia_packet_loss_pct": 0.0, "wikipedia_rtt_min_ms": 6.438, "wikipedia_rtt_max_ms": 6.545, "wikipedia_rtt_avg_ms": 6.504, "wikipedia_rtt_mdev_ms": 0.029, "youtube_packet_loss_pct": 0.0, "youtube_rtt_min_ms": 0.599, "youtube_rtt_max_ms": 0.687, "youtube_rtt_avg_ms": 0.644, "youtube_rtt_mdev_ms": 0.022, "facebook_packet_loss_pct": 0.0, "facebook_rtt_min_ms": 0.875, "facebook_rtt_max_ms": 0.947, "facebook_rtt_avg_ms": 0.912, "facebook_rtt_mdev_ms": 0.018, "tribune_packet_loss_pct": 0.0, "tribune_rtt_min_ms": 0.601, "tribune_rtt_max_ms": 0.646, "tribune_rtt_avg_ms": 0.628, "tribune_rtt_mdev_ms": 0.013, "suntimes_packet_loss_pct": 0.0, "suntimes_rtt_min_ms": 0.671, "suntimes_rtt_max_ms": 0.724, "suntimes_rtt_avg_ms": 0.7, "suntimes_rtt_mdev_ms": 0.013, "uchicago_packet_loss_pct": 0.0, "uchicago_rtt_min_ms": 109.149, "uchicago_rtt_max_ms": 111.866, "uchicago_rtt_avg_ms": 109.491, "uchicago_rtt_mdev_ms": 0.792, "Chicago_packet_loss_pct": 0.0, "Chicago_rtt_min_ms": 103.109, "Chicago_rtt_max_ms": 103.536, "Chicago_rtt_avg_ms": 103.308, "Chicago_rtt_mdev_ms": 0.129, "Washington_DC_error": "Probe IndexError", "Atlanta_packet_loss_pct": 0.0, "Atlanta_rtt_min_ms": 113.836, "Atlanta_rtt_max_ms": 114.183, "Atlanta_rtt_avg_ms": 113.904, "Atlanta_rtt_mdev_ms": 0.095, "Denver_packet_loss_pct": 0.0, "Denver_rtt_min_ms": 125.955, "Denver_rtt_max_ms": 126.077, "Denver_rtt_avg_ms": 125.997, "Denver_rtt_mdev_ms": 0.031, "Seattle_packet_loss_pct": 0.0, "Seattle_rtt_min_ms": 152.646, "Seattle_rtt_max_ms": 153.045, "Seattle_rtt_avg_ms": 152.892, "Seattle_rtt_mdev_ms": 0.117, "Hong_Kong_packet_loss_pct": 0.0, "Hong_Kong_rtt_min_ms": 191.307, "Hong_Kong_rtt_max_ms": 191.425, "Hong_Kong_rtt_avg_ms": 191.343, "Hong_Kong_rtt_mdev_ms": 0.033, "Sydney_packet_loss_pct": 0.0, "Sydney_rtt_min_ms": 247.228, "Sydney_rtt_max_ms": 247.326, "Sydney_rtt_avg_ms": 247.27, "Sydney_rtt_mdev_ms": 0.034, "Johannesburg_packet_loss_pct": 0.0, "Johannesburg_rtt_min_ms": 173.68, "Johannesburg_rtt_max_ms": 174.413, "Johannesburg_rtt_avg_ms": 173.901, "Johannesburg_rtt_mdev_ms": 0.224, "Tunis_packet_loss_pct": 0.0, "Tunis_rtt_min_ms": 36.352, "Tunis_rtt_max_ms": 36.72, "Tunis_rtt_avg_ms": 36.516, "Tunis_rtt_mdev_ms": 0.115, "Paris_packet_loss_pct": 0.0, "Paris_rtt_min_ms": 9.747, "Paris_rtt_max_ms": 13.211, "Paris_rtt_avg_ms": 10.224, "Paris_rtt_mdev_ms": 1.006, "Stockholm_packet_loss_pct": 0.0, "Stockholm_rtt_min_ms": 18.454, "Stockholm_rtt_max_ms": 28.663, "Stockholm_rtt_avg_ms": 19.696, "Stockholm_rtt_mdev_ms": 2.999, "error": true}, "last_mile_rtt": {"1.1.1.1_error": "Probe IndexError", "Cloudflare_DNS_last_mile_ping_packet_loss_pct": 0.0, "Cloudflare_DNS_last_mile_ping_rtt_min_ms": 0.989, "Cloudflare_DNS_last_mile_ping_rtt_max_ms": 2.376, "Cloudflare_DNS_last_mile_ping_rtt_avg_ms": 1.551, "Cloudflare_DNS_last_mile_ping_rtt_mdev_ms": 0.42, "Cloudflare_DNS_last_mile_tr_rtt_min_ms": 0.937, "Cloudflare_DNS_last_mile_tr_rtt_median_ms": 0.99, "Cloudflare_DNS_last_mile_tr_rtt_max_ms": 1.354}, "dns_latency": {"dns_query_avg_ms": 28.75, "dns_query_max_ms": 210, "error": false}, "hops_to_target": {"hops_to_google": 9, "error": false}, "test_bytes_consumed": 0}}