{"Meta": {"Id": null, "Time": 1696153870.855797, "Extended": {"gitlog": "", "dataver": "1", "debhash": "0", "Annotation": null}}, "Measurements": {"total_bytes_consumed": 44812180283, "ipquery": {"ipv4": "3.71.100.200"}, "ping_latency": {"google_packet_loss_pct": 0.0, "google_rtt_min_ms": 0.261, "google_rtt_max_ms": 0.409, "google_rtt_avg_ms": 0.332, "google_rtt_mdev_ms": 0.038, "amazon_packet_loss_pct": 0.0, "amazon_rtt_min_ms": 0.285, "amazon_rtt_max_ms": 0.327, "amazon_rtt_avg_ms": 0.304, "amazon_rtt_mdev_ms": 0.016, "wikipedia_packet_loss_pct": 0.0, "wikipedia_rtt_min_ms": 6.495, "wikipedia_rtt_max_ms": 6.572, "wikipedia_rtt_avg_ms": 6.521, "wikipedia_rtt_mdev_ms": 0.021, "youtube_packet_loss_pct": 0.0, "youtube_rtt_min_ms": 0.611, "youtube_rtt_max_ms": 0.757, "youtube_rtt_avg_ms": 0.649, "youtube_rtt_mdev_ms": 0.04, "facebook_packet_loss_pct": 0.0, "facebook_rtt_min_ms": 1.01, "facebook_rtt_max_ms": 1.071, "facebook_rtt_avg_ms": 1.057, "facebook_rtt_mdev_ms": 0.017, "tribune_packet_loss_pct": 0.0, "tribune_rtt_min_ms": 1.016, "tribune_rtt_max_ms": 1.057, "tribune_rtt_avg_ms": 1.037, "tribune_rtt_mdev_ms": 0.013, "suntimes_packet_loss_pct": 0.0, "suntimes_rtt_min_ms": 0.796, "suntimes_rtt_max_ms": 0.926, "suntimes_rtt_avg_ms": 0.849, "suntimes_rtt_mdev_ms": 0.032, "uchicago_packet_loss_pct": 0.0, "uchicago_rtt_min_ms": 109.285, "uchicago_rtt_max_ms": 109.683, "uchicago_rtt_avg_ms": 109.397, "uchicago_rtt_mdev_ms": 0.123, "Chicago_packet_loss_pct": 0.0, "Chicago_rtt_min_ms": 106.236, "Chicago_rtt_max_ms": 106.394, "Chicago_rtt_avg_ms": 106.298, "Chicago_rtt_mdev_ms": 0.057, "Washington_DC_error": "Probe IndexError", "Atlanta_packet_loss_pct": 0.0, "Atlanta_rtt_min_ms": 99.211, "Atlanta_rtt_max_ms": 99.333, "Atlanta_rtt_avg_ms": 99.259, "Atlanta_rtt_mdev_ms": 0.037, "Denver_packet_loss_pct": 0.0, "Denver_rtt_min_ms": 126.801, "Denver_rtt_max_ms": 126.917, "Denver_rtt_avg_ms": 126.831, "Denver_rtt_mdev_ms": 0.034, "Seattle_packet_loss_pct": 0.0, "Seattle_rtt_min_ms": 155.253, "Seattle_rtt_max_ms": 155.545, "Seattle_rtt_avg_ms": 155.373, "Seattle_rtt_mdev_ms": 0.098, "Hong_Kong_packet_loss_pct": 0.0, "Hong_Kong_rtt_min_ms": 189.898, "Hong_Kong_rtt_max_ms": 190.095, "Hong_Kong_rtt_avg_ms": 189.93, "Hong_Kong_rtt_mdev_ms": 0.056, "Sydney_packet_loss_pct": 0.0, "Sydney_rtt_min_ms": 246.866, "Sydney_rtt_max_ms": 246.965, "Sydney_rtt_avg_ms": 246.911, "Sydney_rtt_mdev_ms": 0.032, "Johannesburg_packet_loss_pct": 0.0, "Johannesburg_rtt_min_ms": 173.195, "Johannesburg_rtt_max_ms": 175.934, "Johannesburg_rtt_avg_ms": 173.607, "Johannesburg_rtt_mdev_ms": 0.779, "Tunis_packet_loss_pct": 0.0, "Tunis_rtt_min_ms": 36.01, "Tunis_rtt_max_ms": 36.536, "Tunis_rtt_avg_ms": 36.182, "Tunis_rtt_mdev_ms": 0.155, "Paris_packet_loss_pct": 0.0, "Paris_rtt_min_ms": 9.916, "Paris_rtt_max_ms": 64.844, "Paris_rtt_avg_ms": 16.045, "Paris_rtt_mdev_ms": 16.299, "Stockholm_packet_loss_pct": 0.0, "Stockholm_rtt_min_ms": 18.778, "Stockholm_rtt_max_ms": 27.765, "Stockholm_rtt_avg_ms": 20.335, "Stockholm_rtt_mdev_ms": 2.788, "error": true}, "last_mile_rtt": {"1.1.1.1_error": "Probe IndexError", "Cloudflare_DNS_last_mile_ping_packet_loss_pct": 0.0, "Cloudflare_DNS_last_mile_ping_rtt_min_ms": 1.13, "Cloudflare_DNS_last_mile_ping_rtt_max_ms": 4.853, "Cloudflare_DNS_last_mile_ping_rtt_avg_ms": 2.053, "Cloudflare_DNS_last_mile_ping_rtt_mdev_ms": 1.052, "Cloudflare_DNS_last_mile_tr_rtt_min_ms": 1.2}, "dns_latency": {"dns_query_avg_ms": 46.25, "dns_query_max_ms": 210, "error": false}, "hops_to_target": {"hops_to_google": 8, "error": false}, "test_bytes_consumed": 0}}