{"Meta": {"Id": null, "Time": 1697291469.072897, "Extended": {"gitlog": "", "dataver": "1", "debhash": "0", "Annotation": null}}, "Measurements": {"total_bytes_consumed": 1573901213841, "ipquery": {"ipv4": "3.71.100.200"}, "ping_latency": {"google_packet_loss_pct": 0.0, "google_rtt_min_ms": 0.574, "google_rtt_max_ms": 0.667, "google_rtt_avg_ms": 0.627, "google_rtt_mdev_ms": 0.023, "amazon_packet_loss_pct": 0.0, "amazon_rtt_min_ms": 0.42, "amazon_rtt_max_ms": 0.504, "amazon_rtt_avg_ms": 0.463, "amazon_rtt_mdev_ms": 0.022, "wikipedia_packet_loss_pct": 0.0, "wikipedia_rtt_min_ms": 6.424, "wikipedia_rtt_max_ms": 6.495, "wikipedia_rtt_avg_ms": 6.476, "wikipedia_rtt_mdev_ms": 0.02, "youtube_packet_loss_pct": 0.0, "youtube_rtt_min_ms": 0.725, "youtube_rtt_max_ms": 0.809, "youtube_rtt_avg_ms": 0.767, "youtube_rtt_mdev_ms": 0.024, "facebook_packet_loss_pct": 0.0, "facebook_rtt_min_ms": 0.995, "facebook_rtt_max_ms": 1.06, "facebook_rtt_avg_ms": 1.029, "facebook_rtt_mdev_ms": 0.016, "tribune_packet_loss_pct": 0.0, "tribune_rtt_min_ms": 0.901, "tribune_rtt_max_ms": 1.047, "tribune_rtt_avg_ms": 0.935, "tribune_rtt_mdev_ms": 0.05, "suntimes_packet_loss_pct": 0.0, "suntimes_rtt_min_ms": 0.672, "suntimes_rtt_max_ms": 0.745, "suntimes_rtt_avg_ms": 0.704, "suntimes_rtt_mdev_ms": 0.017, "uchicago_packet_loss_pct": 0.0, "uchicago_rtt_min_ms": 106.743, "uchicago_rtt_max_ms": 108.339, "uchicago_rtt_avg_ms": 107.2, "uchicago_rtt_mdev_ms": 0.581, "Chicago_packet_loss_pct": 0.0, "Chicago_rtt_min_ms": 106.305, "Chicago_rtt_max_ms": 106.451, "Chicago_rtt_avg_ms": 106.391, "Chicago_rtt_mdev_ms": 0.046, "Washington_DC_error": "Probe IndexError", "Atlanta_packet_loss_pct": 0.0, "Atlanta_rtt_min_ms": 100.596, "Atlanta_rtt_max_ms": 101.435, "Atlanta_rtt_avg_ms": 100.723, "Atlanta_rtt_mdev_ms": 0.239, "Denver_packet_loss_pct": 0.0, "Denver_rtt_min_ms": 141.65, "Denver_rtt_max_ms": 141.702, "Denver_rtt_avg_ms": 141.672, "Denver_rtt_mdev_ms": 0.015, "Seattle_packet_loss_pct": 0.0, "Seattle_rtt_min_ms": 176.107, "Seattle_rtt_max_ms": 176.896, "Seattle_rtt_avg_ms": 176.317, "Seattle_rtt_mdev_ms": 0.223, "Hong_Kong_packet_loss_pct": 0.0, "Hong_Kong_rtt_min_ms": 189.835, "Hong_Kong_rtt_max_ms": 189.939, "Hong_Kong_rtt_avg_ms": 189.863, "Hong_Kong_rtt_mdev_ms": 0.026, "Sydney_packet_loss_pct": 0.0, "Sydney_rtt_min_ms": 247.224, "Sydney_rtt_max_ms": 247.399, "Sydney_rtt_avg_ms": 247.283, "Sydney_rtt_mdev_ms": 0.053, "Johannesburg_packet_loss_pct": 0.0, "Johannesburg_rtt_min_ms": 173.534, "Johannesburg_rtt_max_ms": 174.918, "Johannesburg_rtt_avg_ms": 173.764, "Johannesburg_rtt_mdev_ms": 0.39, "Tunis_packet_loss_pct": 0.0, "Tunis_rtt_min_ms": 34.821, "Tunis_rtt_max_ms": 35.225, "Tunis_rtt_avg_ms": 34.955, "Tunis_rtt_mdev_ms": 0.111, "Paris_packet_loss_pct": 0.0, "Paris_rtt_min_ms": 9.99, "Paris_rtt_max_ms": 11.151, "Paris_rtt_avg_ms": 10.262, "Paris_rtt_mdev_ms": 0.33, "Stockholm_packet_loss_pct": 0.0, "Stockholm_rtt_min_ms": 18.606, "Stockholm_rtt_max_ms": 19.426, "Stockholm_rtt_avg_ms": 18.848, "Stockholm_rtt_mdev_ms": 0.209, "error": true}, "last_mile_rtt": {"1.1.1.1_error": "Probe IndexError", "Cloudflare_DNS_last_mile_ping_packet_loss_pct": 0.0, "Cloudflare_DNS_last_mile_ping_rtt_min_ms": 1.202, "Cloudflare_DNS_last_mile_ping_rtt_max_ms": 69.493, "Cloudflare_DNS_last_mile_ping_rtt_avg_ms": 11.639, "Cloudflare_DNS_last_mile_ping_rtt_mdev_ms": 20.504, "Cloudflare_DNS_last_mile_tr_rtt_min_ms": 0.759, "Cloudflare_DNS_last_mile_tr_rtt_median_ms": 1.165, "Cloudflare_DNS_last_mile_tr_rtt_max_ms": 1.195}, "dns_latency": {"dns_query_avg_ms": 17.5, "dns_query_max_ms": 110, "error": false}, "hops_to_target": {"hops_to_google": 8, "error": false}, "test_bytes_consumed": 0}}